tooldelta/__init__.py
tooldelta/auths.py
tooldelta/constants/__init__.py
tooldelta/constants/minecraft.py
tooldelta/constants/netease.py
tooldelta/constants/packets.py
tooldelta/constants/tooldelta_cfg.py
tooldelta/constants/tooldelta_cli.py
tooldelta/extend_functions/__init__.py
tooldelta/extend_functions/basic.py
tooldelta/extend_functions/gamerule_warnings.py
tooldelta/frame.py
tooldelta/game_utils.py
tooldelta/internal/cmd_executor.py
tooldelta/internal/config_loader.py
tooldelta/internal/launch_cli/__init__.py
tooldelta/internal/launch_cli/eulogist_client.py
tooldelta/internal/launch_cli/eulogist_libs/core_conn.py
tooldelta/internal/launch_cli/fateark_access_point.py
tooldelta/internal/launch_cli/fateark_access_point_indirect.py
tooldelta/internal/launch_cli/fateark_libs/core_conn.py
tooldelta/internal/launch_cli/fateark_libs/proto/README.md
tooldelta/internal/launch_cli/fateark_libs/proto/builder.py
tooldelta/internal/launch_cli/fateark_libs/proto/command_pb2.py
tooldelta/internal/launch_cli/fateark_libs/proto/command_pb2_grpc.py
tooldelta/internal/launch_cli/fateark_libs/proto/listener_pb2.py
tooldelta/internal/launch_cli/fateark_libs/proto/listener_pb2_grpc.py
tooldelta/internal/launch_cli/fateark_libs/proto/playerkit_pb2.py
tooldelta/internal/launch_cli/fateark_libs/proto/playerkit_pb2_grpc.py
tooldelta/internal/launch_cli/fateark_libs/proto/proto/command.proto
tooldelta/internal/launch_cli/fateark_libs/proto/proto/listener.proto
tooldelta/internal/launch_cli/fateark_libs/proto/proto/playerkit.proto
tooldelta/internal/launch_cli/fateark_libs/proto/proto/response.proto
tooldelta/internal/launch_cli/fateark_libs/proto/proto/reversaler.proto
tooldelta/internal/launch_cli/fateark_libs/proto/proto/utils.proto
tooldelta/internal/launch_cli/fateark_libs/proto/response_pb2.py
tooldelta/internal/launch_cli/fateark_libs/proto/response_pb2_grpc.py
tooldelta/internal/launch_cli/fateark_libs/proto/reversaler_pb2.py
tooldelta-1.3.1.dist-info/METADATA
tooldelta-1.3.1.dist-info/WHEEL
tooldelta-1.3.1.dist-info/licenses/LICENSE
tooldelta-1.3.1.dist-info/RECORD
