Metadata-Version: 2.4
Name: Tooldelta
Version: 1.3.1
Summary: Plugin Loader for NeteaseRentalServer on Panel
License-File: LICENSE
Author: ToolDelta Studio Staff
Requires-Python: >=3.10,<3.13
Classifier: Programming Language :: Python :: 3
Classifier: Programming Language :: Python :: 3.10
Classifier: Programming Language :: Python :: 3.11
Classifier: Programming Language :: Python :: 3.12
Requires-Dist: aiohttp (>=3.9.3,<4.0.0)
Requires-Dist: anyio (>=4.4.0,<5.0.0)
Requires-Dist: brotli (>=1.1.0,<2.0.0)
Requires-Dist: colorama (>=0.4.6,<0.5.0)
Requires-Dist: flask (>=3.0.2,<4.0.0)
Requires-Dist: grpcio (>=1.71.0,<2.0.0)
Requires-Dist: msgpack (>=1.1.0,<2.0.0)
Requires-Dist: nbtlib (>=2.0.4,<3.0.0)
Requires-Dist: numpy (>=2.1.0,<3.0.0)
Requires-Dist: protobuf (>=6.30.1,<7.0.0)
Requires-Dist: pyspeedtest (==1.2.7)
Requires-Dist: python-socketio (==5.11.1)
Requires-Dist: pyyaml (==6.0.1)
Requires-Dist: requests (>=2.32.3,<3.0.0)
Requires-Dist: rich (>=14.1.0,<15.0.0)
Requires-Dist: tqdm (>=4.66.4,<5.0.0)
Requires-Dist: websocket-client (>=1.7.0,<2.0.0)
Requires-Dist: websockets (>=12.0,<13.0)
Project-URL: Homepage, https://github.com/ToolDelta-Basic/ToolDelta
Project-URL: Repository, https://github.com/ToolDelta-Basic/ToolDelta
